CINOSUM/__init__.py
CINOSUM/models/CINOSUM.py
CINOSUM/models/__init__.py
CINOSUM/models/encoder.py
CINOSUM/models/generate.py
CINOSUM/models/model_builder.py
CINOSUM/models/neural.py
CINOSUM/models/optimizers.py
CINOSUM/models/rnn.py
CINOSUM-1.1.0.dist-info/METADATA
CINOSUM-1.1.0.dist-info/WHEEL
CINOSUM-1.1.0.dist-info/top_level.txt
CINOSUM-1.1.0.dist-info/RECORD
