Metadata-Version: 2.1
Name: CINOSUM
Version: 1.1.0
Summary: Chinese Minority Extractive Multi-language summarization project
Author: HaoYu Luo
Author-email: 506685820@qq.com
Classifier: Programming Language :: Python :: 3
Classifier: License :: OSI Approved :: MIT License
Classifier: Operating System :: OS Independent
Requires-Python: >=3.8
Requires-Dist: torch
Requires-Dist: numpy
Requires-Dist: tqdm
Requires-Dist: transformers ==4.33.1
